Metadata-Version: 2.4
Name: llm-tldr
Version: 1.5.2
Summary: Token-efficient code analysis for LLMs. 5-layer stack: AST, Call Graph, CFG, DFG, PDG. 95% token savings. 17 languages.
Author: parcadei
Maintainer: parcadei
License: AGPL-3.0
Project-URL: Homepage, https://github.com/parcadei/llm-tldr
Project-URL: Repository, https://github.com/parcadei/llm-tldr
Project-URL: Issues, https://github.com/parcadei/llm-tldr/issues
Project-URL: Documentation, https://github.com/parcadei/llm-tldr#readme
Keywords: code-analysis,llm,ai,tree-sitter,call-graph,cfg,dfg,pdg,mcp,static-analysis
Classifier: Development Status :: 5 - Production/Stable
Classifier: Intended Audience :: Developers
Classifier: License :: OSI Approved :: GNU Affero General Public License v3
Classifier: Operating System :: OS Independent
Classifier: Programming Language :: Python :: 3
Classifier: Programming Language :: Python :: 3.8
Classifier: Programming Language :: Python :: 3.9
Classifier: Programming Language :: Python :: 3.10
Classifier: Programming Language :: Python :: 3.11
Classifier: Programming Language :: Python :: 3.12
Classifier: Topic :: Software Development :: Code Generators
Classifier: Topic :: Software Development :: Documentation
Classifier: Topic :: Text Processing :: Linguistic
Requires-Python: >=3.10
License-File: LICENSE
License-File: NOTICE
Requires-Dist: pygments-tldr>=2.19.1.3
Requires-Dist: requests>=2.25.0
Requires-Dist: mcp>=1.0.0
Requires-Dist: pathspec>=0.12.0
Requires-Dist: tree-sitter>=0.23.0
Requires-Dist: tree-sitter-python>=0.23.0
Requires-Dist: tree-sitter-typescript>=0.23.0
Requires-Dist: tree-sitter-javascript>=0.23.0
Requires-Dist: tree-sitter-go>=0.23.0
Requires-Dist: tree-sitter-rust>=0.23.0
Requires-Dist: tree-sitter-java>=0.23.0
Requires-Dist: tree-sitter-c>=0.21.0
Requires-Dist: tree-sitter-cpp>=0.20.0
Requires-Dist: tree-sitter-ruby>=0.20.0
Requires-Dist: tree-sitter-php>=0.20.0
Requires-Dist: tree-sitter-c-sharp>=0.20.0
Requires-Dist: tree-sitter-kotlin>=1.0.0
Requires-Dist: tree-sitter-scala>=0.23.0
Requires-Dist: tree-sitter-lua<=0.4.1
Requires-Dist: tree-sitter-luau
Requires-Dist: tree-sitter-elixir>=0.3.0
Requires-Dist: sentence-transformers>=5.2.0
Requires-Dist: faiss-cpu>=1.13.2
Requires-Dist: anthropic>=0.75.0
Requires-Dist: tiktoken>=0.12.0
Requires-Dist: rich>=14.2.0
Provides-Extra: ai
Requires-Dist: anthropic>=0.3.0; extra == "ai"
Requires-Dist: openai>=1.0.0; extra == "ai"
Provides-Extra: cli
Requires-Dist: rich>=13.0; extra == "cli"
Requires-Dist: shtab>=1.7.0; extra == "cli"
Provides-Extra: dev
Requires-Dist: pytest>=6.0; extra == "dev"
Requires-Dist: pytest-cov>=2.0; extra == "dev"
Requires-Dist: black>=21.0; extra == "dev"
Requires-Dist: flake8>=3.8; extra == "dev"
Requires-Dist: mypy>=0.900; extra == "dev"
Requires-Dist: rich>=13.0; extra == "dev"
Requires-Dist: shtab>=1.7.0; extra == "dev"
Dynamic: license-file
